easyTCR/__init__.py
easyTCR/easytcr.py
easyTCR-1.0.0.dist-info/LICENSE
easyTCR-1.0.0.dist-info/METADATA
easyTCR-1.0.0.dist-info/WHEEL
easyTCR-1.0.0.dist-info/top_level.txt
easyTCR-1.0.0.dist-info/RECORD
