Metadata-Version: 2.1
Name: easyTCR
Version: 1.0.0
Summary: Explore TCR repertoire
Author-email: gary <gary_dou327@163.com>
Project-URL: Homepage, https://github.com/ZhangLabTJU/easyTCR
Classifier: Programming Language :: Python :: 3
Classifier: License :: OSI Approved :: MIT License
Classifier: Operating System :: OS Independent
Requires-Python: >=3.8
License-File: LICENSE
Requires-Dist: numpy (>=1.20.2)
Requires-Dist: pandas (>=1.2.5)
Requires-Dist: plotnine (>=0.8.0)
Requires-Dist: seaborn (>=0.12.2)
Requires-Dist: matplotlib (>=3.2.2)
Requires-Dist: scipy (>=1.5.3)
